.gitignore
MANIFEST.in
setup.py
ebs/__init__.py
ebs/linuxnode/__init__.py
ebs/linuxnode/gui/__init__.py
ebs/linuxnode/gui/kivy/__init__.py
ebs/linuxnode/gui/kivy/marquee/__init__.py
ebs/linuxnode/gui/kivy/marquee/mixin.py
ebs_linuxnode_gui_kivy_marquee.egg-info/PKG-INFO
ebs_linuxnode_gui_kivy_marquee.egg-info/SOURCES.txt
ebs_linuxnode_gui_kivy_marquee.egg-info/dependency_links.txt
ebs_linuxnode_gui_kivy_marquee.egg-info/requires.txt
ebs_linuxnode_gui_kivy_marquee.egg-info/top_level.txt